{
  "name": "mm1",
  "rules": {
    "source_file": {
      "type": "REPEAT",
      "content": {
        "type": "SYMBOL",
        "name": "statement"
      }
    },
    "whitespace": {
      "type": "REPEAT1",
      "content": {
        "type": "SYMBOL",
        "name": "whitestuff"
      }
    },
    "whitestuff": {
      "type": "CHOICE",
      "members": [
        {
          "type": "SYMBOL",
          "name": "whitechar"
        },
        {
          "type": "SYMBOL",
          "name": "line_comment"
        }
      ]
    },
    "whitechar": {
      "type": "CHOICE",
      "members": [
        {
          "type": "STRING",
          "value": " "
        },
        {
          "type": "STRING",
          "value": "\n"
        }
      ]
    },
    "line_comment": {
      "type": "SEQ",
      "members": [
        {
          "type": "STRING",
          "value": "--"
        },
        {
          "type": "PATTERN",
          "value": "[^\\n]*"
        },
        {
          "type": "STRING",
          "value": "\n"
        }
      ]
    },
    "doc_comment": {
      "type": "SEQ",
      "members": [
        {
          "type": "STRING",
          "value": "--|"
        },
        {
          "type": "PATTERN",
          "value": "[^\\n]*"
        },
        {
          "type": "STRING",
          "value": "\n"
        }
      ]
    },
    "number": {
      "type": "CHOICE",
      "members": [
        {
          "type": "STRING",
          "value": "0"
        },
        {
          "type": "SEQ",
          "members": [
            {
              "type": "PATTERN",
              "value": "[1-9]"
            },
            {
              "type": "PATTERN",
              "value": "[0-9]*"
            }
          ]
        }
      ]
    },
    "math_string": {
      "type": "SEQ",
      "members": [
        {
          "type": "STRING",
          "value": "$"
        },
        {
          "type": "PATTERN",
          "value": "[^\\$]*"
        },
        {
          "type": "STRING",
          "value": "$"
        }
      ]
    },
    "identifier": {
      "type": "PATTERN",
      "value": "[a-zA-Z_][a-zA-Z0-9_]*"
    },
    "statement": {
      "type": "CHOICE",
      "members": [
        {
          "type": "SYMBOL",
          "name": "sort_stmt"
        },
        {
          "type": "SYMBOL",
          "name": "line_comment"
        },
        {
          "type": "SYMBOL",
          "name": "doc_comment"
        },
        {
          "type": "SYMBOL",
          "name": "notation_stmt"
        },
        {
          "type": "SYMBOL",
          "name": "inout_stmt"
        },
        {
          "type": "SYMBOL",
          "name": "decl_stmt"
        },
        {
          "type": "SYMBOL",
          "name": "do_stmt"
        },
        {
          "type": "SYMBOL",
          "name": "annot_stmt"
        }
      ]
    },
    "sort_mod": {
      "type": "CHOICE",
      "members": [
        {
          "type": "STRING",
          "value": "pure"
        },
        {
          "type": "STRING",
          "value": "strict"
        },
        {
          "type": "STRING",
          "value": "provable"
        },
        {
          "type": "STRING",
          "value": "free"
        }
      ]
    },
    "visibility": {
      "type": "CHOICE",
      "members": [
        {
          "type": "STRING",
          "value": "pub"
        },
        {
          "type": "STRING",
          "value": "abstract"
        },
        {
          "type": "STRING",
          "value": "local"
        }
      ]
    },
    "decl_kind": {
      "type": "CHOICE",
      "members": [
        {
          "type": "STRING",
          "value": "term"
        },
        {
          "type": "STRING",
          "value": "axiom"
        },
        {
          "type": "STRING",
          "value": "def"
        },
        {
          "type": "STRING",
          "value": "theorem"
        }
      ]
    },
    "decl_stmt": {
      "type": "SEQ",
      "members": [
        {
          "type": "FIELD",
          "name": "vis",
          "content": {
            "type": "CHOICE",
            "members": [
              {
                "type": "SYMBOL",
                "name": "visibility"
              },
              {
                "type": "BLANK"
              }
            ]
          }
        },
        {
          "type": "FIELD",
          "name": "k",
          "content": {
            "type": "SYMBOL",
            "name": "decl_kind"
          }
        },
        {
          "type": "FIELD",
          "name": "id",
          "content": {
            "type": "SYMBOL",
            "name": "identifier"
          }
        },
        {
          "type": "FIELD",
          "name": "bis",
          "content": {
            "type": "ALIAS",
            "content": {
              "type": "REPEAT",
              "content": {
                "type": "SYMBOL",
                "name": "binder"
              }
            },
            "named": true,
            "value": "binder_list"
          }
        },
        {
          "type": "CHOICE",
          "members": [
            {
              "type": "SEQ",
              "members": [
                {
                  "type": "STRING",
                  "value": ":"
                },
                {
                  "type": "FIELD",
                  "name": "type",
                  "content": {
                    "type": "SYMBOL",
                    "name": "arrow_type"
                  }
                }
              ]
            },
            {
              "type": "BLANK"
            }
          ]
        },
        {
          "type": "CHOICE",
          "members": [
            {
              "type": "SEQ",
              "members": [
                {
                  "type": "STRING",
                  "value": "="
                },
                {
                  "type": "FIELD",
                  "name": "val",
                  "content": {
                    "type": "SYMBOL",
                    "name": "sexpr"
                  }
                }
              ]
            },
            {
              "type": "BLANK"
            }
          ]
        },
        {
          "type": "STRING",
          "value": ";"
        }
      ]
    },
    "type_or_fmla": {
      "type": "CHOICE",
      "members": [
        {
          "type": "SYMBOL",
          "name": "type"
        },
        {
          "type": "ALIAS",
          "content": {
            "type": "SYMBOL",
            "name": "math_string"
          },
          "named": true,
          "value": "formula"
        }
      ]
    },
    "binder_contents": {
      "type": "SEQ",
      "members": [
        {
          "type": "ALIAS",
          "content": {
            "type": "REPEAT1",
            "content": {
              "type": "FIELD",
              "name": "local",
              "content": {
                "type": "SYMBOL",
                "name": "var_decl"
              }
            }
          },
          "named": true,
          "value": "local_list"
        },
        {
          "type": "CHOICE",
          "members": [
            {
              "type": "SEQ",
              "members": [
                {
                  "type": "STRING",
                  "value": ":"
                },
                {
                  "type": "FIELD",
                  "name": "ty",
                  "content": {
                    "type": "SYMBOL",
                    "name": "type_or_fmla"
                  }
                }
              ]
            },
            {
              "type": "BLANK"
            }
          ]
        }
      ]
    },
    "binder": {
      "type": "CHOICE",
      "members": [
        {
          "type": "SEQ",
          "members": [
            {
              "type": "STRING",
              "value": "{"
            },
            {
              "type": "SYMBOL",
              "name": "binder_contents"
            },
            {
              "type": "STRING",
              "value": "}"
            }
          ]
        },
        {
          "type": "SEQ",
          "members": [
            {
              "type": "STRING",
              "value": "("
            },
            {
              "type": "SYMBOL",
              "name": "binder_contents"
            },
            {
              "type": "STRING",
              "value": ")"
            }
          ]
        }
      ]
    },
    "var_decl": {
      "type": "SEQ",
      "members": [
        {
          "type": "CHOICE",
          "members": [
            {
              "type": "STRING",
              "value": "."
            },
            {
              "type": "BLANK"
            }
          ]
        },
        {
          "type": "SYMBOL",
          "name": "identifier_"
        }
      ]
    },
    "arrow_type": {
      "type": "CHOICE",
      "members": [
        {
          "type": "SYMBOL",
          "name": "type_or_fmla"
        },
        {
          "type": "SEQ",
          "members": [
            {
              "type": "SYMBOL",
              "name": "type_or_fmla"
            },
            {
              "type": "STRING",
              "value": ">"
            },
            {
              "type": "SYMBOL",
              "name": "arrow_type"
            }
          ]
        }
      ]
    },
    "sort_stmt": {
      "type": "SEQ",
      "members": [
        {
          "type": "FIELD",
          "name": "mods",
          "content": {
            "type": "REPEAT",
            "content": {
              "type": "SYMBOL",
              "name": "sort_mod"
            }
          }
        },
        {
          "type": "STRING",
          "value": "sort"
        },
        {
          "type": "FIELD",
          "name": "id",
          "content": {
            "type": "SYMBOL",
            "name": "identifier"
          }
        },
        {
          "type": "STRING",
          "value": ";"
        }
      ]
    },
    "type": {
      "type": "SEQ",
      "members": [
        {
          "type": "SYMBOL",
          "name": "identifier"
        },
        {
          "type": "REPEAT",
          "content": {
            "type": "SYMBOL",
            "name": "identifier"
          }
        }
      ]
    },
    "identifier_": {
      "type": "CHOICE",
      "members": [
        {
          "type": "SYMBOL",
          "name": "identifier"
        },
        {
          "type": "STRING",
          "value": "_"
        }
      ]
    },
    "notation_stmt": {
      "type": "CHOICE",
      "members": [
        {
          "type": "SYMBOL",
          "name": "delimiter_stmt"
        },
        {
          "type": "SYMBOL",
          "name": "simple_notation_stmt"
        },
        {
          "type": "SYMBOL",
          "name": "coercion_stmt"
        },
        {
          "type": "SYMBOL",
          "name": "gen_notation_stmt"
        }
      ]
    },
    "delimiter_stmt": {
      "type": "SEQ",
      "members": [
        {
          "type": "STRING",
          "value": "delimiter"
        },
        {
          "type": "SYMBOL",
          "name": "math_string"
        },
        {
          "type": "CHOICE",
          "members": [
            {
              "type": "SYMBOL",
              "name": "math_string"
            },
            {
              "type": "BLANK"
            }
          ]
        },
        {
          "type": "STRING",
          "value": ";"
        }
      ]
    },
    "simple_notation_stmt": {
      "type": "SEQ",
      "members": [
        {
          "type": "CHOICE",
          "members": [
            {
              "type": "STRING",
              "value": "infixl"
            },
            {
              "type": "STRING",
              "value": "infixr"
            },
            {
              "type": "STRING",
              "value": "prefix"
            }
          ]
        },
        {
          "type": "SYMBOL",
          "name": "identifier"
        },
        {
          "type": "STRING",
          "value": ":"
        },
        {
          "type": "ALIAS",
          "content": {
            "type": "SYMBOL",
            "name": "math_string"
          },
          "named": true,
          "value": "constant"
        },
        {
          "type": "STRING",
          "value": "prec"
        },
        {
          "type": "SYMBOL",
          "name": "precedence_lvl"
        },
        {
          "type": "STRING",
          "value": ";"
        }
      ]
    },
    "precedence_lvl": {
      "type": "CHOICE",
      "members": [
        {
          "type": "SYMBOL",
          "name": "number"
        },
        {
          "type": "STRING",
          "value": "max"
        }
      ]
    },
    "coercion_stmt": {
      "type": "SEQ",
      "members": [
        {
          "type": "STRING",
          "value": "coercion"
        },
        {
          "type": "FIELD",
          "name": "id",
          "content": {
            "type": "SYMBOL",
            "name": "identifier"
          }
        },
        {
          "type": "STRING",
          "value": ":"
        },
        {
          "type": "FIELD",
          "name": "from",
          "content": {
            "type": "SYMBOL",
            "name": "identifier"
          }
        },
        {
          "type": "STRING",
          "value": ">"
        },
        {
          "type": "FIELD",
          "name": "to",
          "content": {
            "type": "SYMBOL",
            "name": "identifier"
          }
        },
        {
          "type": "STRING",
          "value": ";"
        }
      ]
    },
    "gen_notation_stmt": {
      "type": "SEQ",
      "members": [
        {
          "type": "STRING",
          "value": "notation"
        },
        {
          "type": "FIELD",
          "name": "id",
          "content": {
            "type": "SYMBOL",
            "name": "identifier"
          }
        },
        {
          "type": "FIELD",
          "name": "bis",
          "content": {
            "type": "ALIAS",
            "content": {
              "type": "REPEAT",
              "content": {
                "type": "SYMBOL",
                "name": "binder"
              }
            },
            "named": true,
            "value": "binder_list"
          }
        },
        {
          "type": "CHOICE",
          "members": [
            {
              "type": "SEQ",
              "members": [
                {
                  "type": "STRING",
                  "value": ":"
                },
                {
                  "type": "FIELD",
                  "name": "ty",
                  "content": {
                    "type": "SYMBOL",
                    "name": "type"
                  }
                }
              ]
            },
            {
              "type": "BLANK"
            }
          ]
        },
        {
          "type": "STRING",
          "value": "="
        },
        {
          "type": "FIELD",
          "name": "prec",
          "content": {
            "type": "SYMBOL",
            "name": "prec_constant"
          }
        },
        {
          "type": "FIELD",
          "name": "lits",
          "content": {
            "type": "REPEAT",
            "content": {
              "type": "SYMBOL",
              "name": "notation_literal"
            }
          }
        },
        {
          "type": "STRING",
          "value": ";"
        }
      ]
    },
    "notation_literal": {
      "type": "CHOICE",
      "members": [
        {
          "type": "SYMBOL",
          "name": "prec_constant"
        },
        {
          "type": "SYMBOL",
          "name": "identifier"
        }
      ]
    },
    "prec_constant": {
      "type": "SEQ",
      "members": [
        {
          "type": "STRING",
          "value": "("
        },
        {
          "type": "ALIAS",
          "content": {
            "type": "SYMBOL",
            "name": "math_string"
          },
          "named": true,
          "value": "constant"
        },
        {
          "type": "STRING",
          "value": ":"
        },
        {
          "type": "SYMBOL",
          "name": "precedence_lvl"
        },
        {
          "type": "STRING",
          "value": ")"
        }
      ]
    },
    "inout_stmt": {
      "type": "CHOICE",
      "members": [
        {
          "type": "SYMBOL",
          "name": "input_stmt"
        },
        {
          "type": "SYMBOL",
          "name": "output_stmt"
        }
      ]
    },
    "input_stmt": {
      "type": "SEQ",
      "members": [
        {
          "type": "STRING",
          "value": "input"
        },
        {
          "type": "ALIAS",
          "content": {
            "type": "SYMBOL",
            "name": "identifier"
          },
          "named": true,
          "value": "input_kind"
        },
        {
          "type": "STRING",
          "value": ":"
        },
        {
          "type": "REPEAT",
          "content": {
            "type": "CHOICE",
            "members": [
              {
                "type": "SYMBOL",
                "name": "identifier"
              },
              {
                "type": "SYMBOL",
                "name": "math_string"
              }
            ]
          }
        },
        {
          "type": "STRING",
          "value": ";"
        }
      ]
    },
    "output_stmt": {
      "type": "SEQ",
      "members": [
        {
          "type": "STRING",
          "value": "output"
        },
        {
          "type": "ALIAS",
          "content": {
            "type": "SYMBOL",
            "name": "identifier"
          },
          "named": true,
          "value": "output_kind"
        },
        {
          "type": "STRING",
          "value": ":"
        },
        {
          "type": "REPEAT",
          "content": {
            "type": "CHOICE",
            "members": [
              {
                "type": "SYMBOL",
                "name": "identifier"
              },
              {
                "type": "SYMBOL",
                "name": "math_string"
              }
            ]
          }
        },
        {
          "type": "STRING",
          "value": ";"
        }
      ]
    },
    "init": {
      "type": "CHOICE",
      "members": [
        {
          "type": "PATTERN",
          "value": "[a-z]"
        },
        {
          "type": "PATTERN",
          "value": "[A-Z]"
        },
        {
          "type": "PATTERN",
          "value": "[!%&*\\/:<=>?^_~]"
        }
      ]
    },
    "atom": {
      "type": "PREC_LEFT",
      "value": 1,
      "content": {
        "type": "CHOICE",
        "members": [
          {
            "type": "SEQ",
            "members": [
              {
                "type": "SYMBOL",
                "name": "init"
              },
              {
                "type": "ALIAS",
                "content": {
                  "type": "TOKEN",
                  "content": {
                    "type": "REPEAT",
                    "content": {
                      "type": "CHOICE",
                      "members": [
                        {
                          "type": "PATTERN",
                          "value": "[a-z]"
                        },
                        {
                          "type": "PATTERN",
                          "value": "[A-Z]"
                        },
                        {
                          "type": "PATTERN",
                          "value": "[0-9]"
                        },
                        {
                          "type": "PATTERN",
                          "value": "[!%&*\\/:<=>?^_~+-.@]"
                        }
                      ]
                    }
                  }
                },
                "named": true,
                "value": "subsequent"
              }
            ]
          },
          {
            "type": "SEQ",
            "members": [
              {
                "type": "STRING",
                "value": "->"
              },
              {
                "type": "ALIAS",
                "content": {
                  "type": "TOKEN",
                  "content": {
                    "type": "REPEAT",
                    "content": {
                      "type": "CHOICE",
                      "members": [
                        {
                          "type": "PATTERN",
                          "value": "[a-z]"
                        },
                        {
                          "type": "PATTERN",
                          "value": "[A-Z]"
                        },
                        {
                          "type": "PATTERN",
                          "value": "[0-9]"
                        },
                        {
                          "type": "PATTERN",
                          "value": "[!%&*\\/:<=>?^_~+-.@]"
                        }
                      ]
                    }
                  }
                },
                "named": true,
                "value": "subsequent"
              }
            ]
          },
          {
            "type": "STRING",
            "value": "+"
          },
          {
            "type": "STRING",
            "value": "-"
          },
          {
            "type": "STRING",
            "value": "..."
          }
        ]
      }
    },
    "sexpr": {
      "type": "CHOICE",
      "members": [
        {
          "type": "SYMBOL",
          "name": "atom"
        },
        {
          "type": "SYMBOL",
          "name": "list"
        },
        {
          "type": "SYMBOL",
          "name": "number"
        },
        {
          "type": "SYMBOL",
          "name": "sexpr_string"
        },
        {
          "type": "SYMBOL",
          "name": "sexpr_bool"
        },
        {
          "type": "STRING",
          "value": "#undef"
        },
        {
          "type": "ALIAS",
          "content": {
            "type": "SYMBOL",
            "name": "math_string"
          },
          "named": true,
          "value": "formula"
        },
        {
          "type": "SEQ",
          "members": [
            {
              "type": "STRING",
              "value": "'"
            },
            {
              "type": "SYMBOL",
              "name": "sexpr"
            }
          ]
        },
        {
          "type": "SEQ",
          "members": [
            {
              "type": "STRING",
              "value": ","
            },
            {
              "type": "SYMBOL",
              "name": "sexpr"
            }
          ]
        }
      ]
    },
    "do_stmt": {
      "type": "CHOICE",
      "members": [
        {
          "type": "SYMBOL",
          "name": "do_block"
        },
        {
          "type": "SYMBOL",
          "name": "do_inline"
        }
      ]
    },
    "do_block": {
      "type": "PREC",
      "value": 2,
      "content": {
        "type": "SEQ",
        "members": [
          {
            "type": "STRING",
            "value": "do"
          },
          {
            "type": "STRING",
            "value": "{"
          },
          {
            "type": "REPEAT",
            "content": {
              "type": "PREC",
              "value": 2,
              "content": {
                "type": "CHOICE",
                "members": [
                  {
                    "type": "SYMBOL",
                    "name": "sexpr"
                  },
                  {
                    "type": "SYMBOL",
                    "name": "line_comment"
                  },
                  {
                    "type": "SYMBOL",
                    "name": "doc_comment"
                  }
                ]
              }
            }
          },
          {
            "type": "STRING",
            "value": "}"
          },
          {
            "type": "STRING",
            "value": ";"
          }
        ]
      }
    },
    "do_inline": {
      "type": "SEQ",
      "members": [
        {
          "type": "STRING",
          "value": "do"
        },
        {
          "type": "REPEAT1",
          "content": {
            "type": "PREC",
            "value": 1,
            "content": {
              "type": "SYMBOL",
              "name": "sexpr"
            }
          }
        },
        {
          "type": "STRING",
          "value": ";"
        }
      ]
    },
    "list": {
      "type": "CHOICE",
      "members": [
        {
          "type": "PREC_RIGHT",
          "value": 2,
          "content": {
            "type": "SEQ",
            "members": [
              {
                "type": "STRING",
                "value": "@"
              },
              {
                "type": "ALIAS",
                "content": {
                  "type": "CHOICE",
                  "members": [
                    {
                      "type": "REPEAT",
                      "content": {
                        "type": "SYMBOL",
                        "name": "sexpr"
                      }
                    },
                    {
                      "type": "SEQ",
                      "members": [
                        {
                          "type": "REPEAT1",
                          "content": {
                            "type": "SYMBOL",
                            "name": "sexpr"
                          }
                        },
                        {
                          "type": "STRING",
                          "value": "."
                        },
                        {
                          "type": "SYMBOL",
                          "name": "sexpr"
                        }
                      ]
                    }
                  ]
                },
                "named": true,
                "value": "list_inner"
              }
            ]
          }
        },
        {
          "type": "SEQ",
          "members": [
            {
              "type": "STRING",
              "value": "("
            },
            {
              "type": "ALIAS",
              "content": {
                "type": "CHOICE",
                "members": [
                  {
                    "type": "REPEAT",
                    "content": {
                      "type": "SYMBOL",
                      "name": "sexpr"
                    }
                  },
                  {
                    "type": "SEQ",
                    "members": [
                      {
                        "type": "REPEAT1",
                        "content": {
                          "type": "SYMBOL",
                          "name": "sexpr"
                        }
                      },
                      {
                        "type": "STRING",
                        "value": "."
                      },
                      {
                        "type": "SYMBOL",
                        "name": "sexpr"
                      }
                    ]
                  }
                ]
              },
              "named": true,
              "value": "list_inner"
            },
            {
              "type": "STRING",
              "value": ")"
            }
          ]
        },
        {
          "type": "SEQ",
          "members": [
            {
              "type": "STRING",
              "value": "["
            },
            {
              "type": "ALIAS",
              "content": {
                "type": "CHOICE",
                "members": [
                  {
                    "type": "REPEAT",
                    "content": {
                      "type": "SYMBOL",
                      "name": "sexpr"
                    }
                  },
                  {
                    "type": "SEQ",
                    "members": [
                      {
                        "type": "REPEAT1",
                        "content": {
                          "type": "SYMBOL",
                          "name": "sexpr"
                        }
                      },
                      {
                        "type": "STRING",
                        "value": "."
                      },
                      {
                        "type": "SYMBOL",
                        "name": "sexpr"
                      }
                    ]
                  }
                ]
              },
              "named": true,
              "value": "list_inner"
            },
            {
              "type": "STRING",
              "value": "]"
            }
          ]
        },
        {
          "type": "ALIAS",
          "content": {
            "type": "SEQ",
            "members": [
              {
                "type": "STRING",
                "value": "{"
              },
              {
                "type": "ALIAS",
                "content": {
                  "type": "CHOICE",
                  "members": [
                    {
                      "type": "REPEAT",
                      "content": {
                        "type": "SYMBOL",
                        "name": "sexpr"
                      }
                    },
                    {
                      "type": "SEQ",
                      "members": [
                        {
                          "type": "REPEAT1",
                          "content": {
                            "type": "SYMBOL",
                            "name": "sexpr"
                          }
                        },
                        {
                          "type": "STRING",
                          "value": "."
                        },
                        {
                          "type": "SYMBOL",
                          "name": "sexpr"
                        }
                      ]
                    }
                  ]
                },
                "named": true,
                "value": "list_inner"
              },
              {
                "type": "STRING",
                "value": "}"
              }
            ]
          },
          "named": true,
          "value": "curly_list"
        }
      ]
    },
    "sexpr_number": {
      "type": "CHOICE",
      "members": [
        {
          "type": "REPEAT1",
          "content": {
            "type": "PATTERN",
            "value": "[0-9]"
          }
        },
        {
          "type": "SEQ",
          "members": [
            {
              "type": "STRING",
              "value": "0"
            },
            {
              "type": "CHOICE",
              "members": [
                {
                  "type": "STRING",
                  "value": "x"
                },
                {
                  "type": "STRING",
                  "value": "X"
                }
              ]
            },
            {
              "type": "REPEAT1",
              "content": {
                "type": "PATTERN",
                "value": "[0-9a-fA-F]"
              }
            }
          ]
        }
      ]
    },
    "sexpr_string": {
      "type": "PREC",
      "value": 30,
      "content": {
        "type": "SEQ",
        "members": [
          {
            "type": "STRING",
            "value": "\""
          },
          {
            "type": "REPEAT",
            "content": {
              "type": "SYMBOL",
              "name": "sexpr_char"
            }
          },
          {
            "type": "STRING",
            "value": "\""
          }
        ]
      }
    },
    "sexpr_char": {
      "type": "PREC",
      "value": 40,
      "content": {
        "type": "CHOICE",
        "members": [
          {
            "type": "PATTERN",
            "value": "[^\\\"\\\\]"
          },
          {
            "type": "STRING",
            "value": "\""
          },
          {
            "type": "STRING",
            "value": "\\"
          },
          {
            "type": "STRING",
            "value": "\n"
          },
          {
            "type": "STRING",
            "value": "\r"
          }
        ]
      }
    },
    "sexpr_bool": {
      "type": "CHOICE",
      "members": [
        {
          "type": "STRING",
          "value": "#t"
        },
        {
          "type": "STRING",
          "value": "#f"
        }
      ]
    },
    "annot_stmt": {
      "type": "SEQ",
      "members": [
        {
          "type": "STRING",
          "value": "@"
        },
        {
          "type": "SYMBOL",
          "name": "sexpr"
        },
        {
          "type": "SYMBOL",
          "name": "statement"
        }
      ]
    }
  },
  "extras": [
    {
      "type": "PATTERN",
      "value": "\\s"
    }
  ],
  "conflicts": [],
  "externals": [],
  "inline": [
    "binder_contents"
  ],
  "supertypes": []
}

